odoo/addons/ssi_fingerspot/README.rst
odoo/addons/ssi_fingerspot/__init__.py
odoo/addons/ssi_fingerspot/__manifest__.py
odoo/addons/ssi_fingerspot/menu.xml
odoo/addons/ssi_fingerspot/data/approval_template_data.xml
odoo/addons/ssi_fingerspot/data/base_automation_data.xml
odoo/addons/ssi_fingerspot/data/hr_attendance_reason.xml
odoo/addons/ssi_fingerspot/data/ir_actions_server_data.xml
odoo/addons/ssi_fingerspot/data/ir_cron.xml
odoo/addons/ssi_fingerspot/data/ir_cron_import_attendance.xml
odoo/addons/ssi_fingerspot/data/ir_sequence_data.xml
odoo/addons/ssi_fingerspot/data/policy_template_data.xml
odoo/addons/ssi_fingerspot/data/sequence_template_data.xml
odoo/addons/ssi_fingerspot/models/__init__.py
odoo/addons/ssi_fingerspot/models/fingerspot_attendance_machine.py
odoo/addons/ssi_fingerspot/models/fingerspot_attendance_machine_batch.py
odoo/addons/ssi_fingerspot/models/fingerspot_backend.py
odoo/addons/ssi_fingerspot/models/fingerspot_data_machine.py
odoo/addons/ssi_fingerspot/models/fingerspot_machine_user.py
odoo/addons/ssi_fingerspot/models/hr_timesheet_attendance.py
odoo/addons/ssi_fingerspot/models/res_company.py
odoo/addons/ssi_fingerspot/security/ir.model.access.csv
odoo/addons/ssi_fingerspot/security/ir_module_category_data.xml
odoo/addons/ssi_fingerspot/security/ir_rule_data.xml
odoo/addons/ssi_fingerspot/security/res_group_data.xml
odoo/addons/ssi_fingerspot/static/description/icon.png
odoo/addons/ssi_fingerspot/views/fingerspot_attendance_machine_batch_views.xml
odoo/addons/ssi_fingerspot/views/fingerspot_attendance_machine_views.xml
odoo/addons/ssi_fingerspot/views/fingerspot_backend_views.xml
odoo/addons/ssi_fingerspot/views/fingerspot_data_machine_views.xml
odoo/addons/ssi_fingerspot/views/hr_timesheet_attendance_views.xml
odoo/addons/ssi_fingerspot/views/res_company_views.xml
odoo14_addon_ssi_fingerspot-14.0.3.0.0.dist-info/METADATA
odoo14_addon_ssi_fingerspot-14.0.3.0.0.dist-info/WHEEL
odoo14_addon_ssi_fingerspot-14.0.3.0.0.dist-info/top_level.txt
odoo14_addon_ssi_fingerspot-14.0.3.0.0.dist-info/RECORD
