Metadata-Version: 2.1
Name: odoo14-addon-ssi-fingerspot
Version: 14.0.3.0.0
Summary: Fingerspot Attendance Machine Integration with Odoo
Home-page: https://simetri-sinergi.id
Author: OpenSynergy Indonesia, PT. Simetri Sinergi Indonesia
License: AGPL-3
Platform: UNKNOWN
Classifier: Programming Language :: Python
Classifier: Framework :: Odoo
Classifier: Framework :: Odoo :: 14.0
Classifier: License :: OSI Approved :: GNU Affero General Public License v3
Requires-Python: >=3.6
Requires-Dist: odoo14-addon-ssi-m2o-configurator-mixin
Requires-Dist: odoo14-addon-ssi-master-data-mixin
Requires-Dist: odoo14-addon-ssi-timesheet-attendance
Requires-Dist: odoo14-addon-ssi-transaction-cancel-mixin
Requires-Dist: odoo14-addon-ssi-transaction-confirm-mixin
Requires-Dist: odoo14-addon-ssi-transaction-date-duration-mixin
Requires-Dist: odoo14-addon-ssi-transaction-done-mixin
Requires-Dist: odoo14-addon-ssi-transaction-queue-cancel-mixin
Requires-Dist: odoo14-addon-ssi-transaction-queue-done-mixin
Requires-Dist: odoo <14.1dev,>=14.0a
Requires-Dist: pandas
